{
    "pools": [
        {
            "entries": [
                {
                    "type": "minecraft:item",
                    "name": "minecraft:carrot_on_a_stick",
                    "functions": [
                        {
                            "function": "minecraft:set_nbt",
                            "tag": "{CustomModelData: 120011, display: {Name: '[{\"translate\":\"item.dreamland.dream_breaker\",\"italic\":false}]'},id: \"dreamland:dream_breaker\", dreamland: {isTemp: 0b}}"
                        }
                    ]
                }
            ],
            "rolls": 1
        }
    ]
}